pkm_installer/__init__.py
pkm_installer/directories.py
pkm_installer/installer.py
pkm_installer/venvs.py
pkm_installer-0.2.2.dist-info/WHEEL
pkm_installer-0.2.2.dist-info/METADATA
pkm_installer-0.2.2.dist-info/RECORD
